{
  "id": "about",
  "label": "about",
  "repeatable": false,
  "status": true,
  "json": {
    "Main": {
      "title": {
        "type": "StructuredText",
        "config": {
          "label": "Title",
          "placeholder": "",
          "allowTargetBlank": true,
          "single": "heading1"
        }
      },
      "description": {
        "type": "StructuredText",
        "config": {
          "label": "Description",
          "placeholder": "",
          "allowTargetBlank": true,
          "multi": "paragraph,preformatted,heading1,heading2,heading3,heading4,heading5,heading6,strong,em,hyperlink,image,embed,list-item,o-list-item,rtl"
        }
      },
      "banner": {
        "type": "Image",
        "config": {
          "label": "Banner",
          "constraint": {},
          "thumbnails": []
        }
      },
      "instagram": {
        "type": "Link",
        "config": {
          "label": "Instagram",
          "placeholder": "",
          "select": null
        }
      },
      "linkedin": {
        "type": "Link",
        "config": {
          "label": "Linkedin",
          "placeholder": "",
          "select": null
        }
      },
      "github": {
        "type": "Link",
        "config": {
          "label": "Github",
          "placeholder": "",
          "select": null
        }
      }
    }
  }
}